CoolProp-stubs/__init__.pyi
CoolProp-stubs/CoolProp/__init__.pyi
cycler-stubs/__init__.pyi
hurst-stubs/__init__.pyi
matplotlib-stubs/__init__.pyi
matplotlib-stubs/animation.pyi
matplotlib-stubs/cm.pyi
matplotlib-stubs/colors.pyi
matplotlib-stubs/figure.pyi
matplotlib-stubs/ticker.pyi
matplotlib-stubs/pyplot/__init__.pyi
matplotlib-stubs/pyplot/style.pyi
mpl_toolkits-stubs/__init__.pyi
mpl_toolkits-stubs/mplot.pyi
numba-stubs/__init__.pyi
python_translator-stubs/__init__.pyi
scienceplots-stubs/__init__.pyi
scientific_plots/__init__.py
scientific_plots/default_plots.py
scientific_plots/plot_settings.py
scientific_plots/py.typed
scientific_plots/types_.py
scientific_plots/utilities.py
scientific_plots-1.9.9.dist-info/licenses/COPYING.LESSER
scipy-stubs/__init__.pyi
scipy-stubs/constants.pyi
scipy-stubs/fft.pyi
scipy-stubs/integrate.pyi
scipy-stubs/interpolate.pyi
scipy-stubs/optimize.pyi
scipy-stubs/special.pyi
scipy-stubs/stats.pyi
scipy-stubs/signal/__init__.pyi
scipy-stubs/signal/windows.pyi
skimage-stubs/filters.pyi
sklearn-stubs/ensemble.pyi
scientific_plots-1.9.9.dist-info/METADATA
scientific_plots-1.9.9.dist-info/WHEEL
scientific_plots-1.9.9.dist-info/top_level.txt
scientific_plots-1.9.9.dist-info/RECORD
