Metadata-Version: 2.4
Name: scientific_plots
Version: 1.9.9
Summary: Useful methods for plots used in science
Author-email: Felix Fischer <f.fischer@ifas.rwth-aachen.de>
License:                    GNU LESSER GENERAL PUBLIC LICENSE
Project-URL: Homepage, https://git.rwth-aachen.de/pneumatics/python_module
Project-URL: Bug Tracker, https://git.rwth-aachen.de/pneumatics/python_module/-/issues
Keywords: Plotting,science,library,utilities,styling
Classifier: License :: OSI Approved :: GNU Lesser General Public License v3 or later (LGPLv3+)
Classifier: Programming Language :: Python
Classifier: Programming Language :: Python :: 3
Classifier: Programming Language :: Python :: 3
Requires-Python: >=3.10
License-File: COPYING.LESSER
Requires-Dist: scipy
Requires-Dist: numpy>=1.21
Requires-Dist: matplotlib>=3.7
Requires-Dist: SciencePlots
Requires-Dist: python_translator
Requires-Dist: requests
Requires-Dist: beautifulsoup4
Requires-Dist: urllib3>=2.0.0
Requires-Dist: pytest
Provides-Extra: dev
Requires-Dist: mypy; extra == "dev"
Requires-Dist: pylint; extra == "dev"
Requires-Dist: flake8; extra == "dev"
Requires-Dist: types-urllib3; extra == "dev"
Requires-Dist: twine>=4.0.0; extra == "dev"
Requires-Dist: requests-toolbelt>=1.0.0; extra == "dev"
Dynamic: license-file
